odbcutils/__init__.py
odbcutils/odbcutils.py
odbcutils/py.typed
odbcutils-0.2.1.dist-info/LICENSE
odbcutils-0.2.1.dist-info/METADATA
odbcutils-0.2.1.dist-info/WHEEL
odbcutils-0.2.1.dist-info/top_level.txt
odbcutils-0.2.1.dist-info/RECORD
