Metadata-Version: 2.1
Name: odbcutils
Version: 0.2.1
Summary: A small helper library for executing SQL using pyodbc
Home-page: http://github.com/geographika/odbcutils
Author: Seth Girvin
Author-email: sethg@geographika.co.uk
License: MIT
Classifier: Development Status :: 3 - Alpha
Classifier: License :: OSI Approved :: MIT License
Classifier: Programming Language :: Python :: 3.10
Classifier: Intended Audience :: Developers
Classifier: Topic :: Database
License-File: LICENSE
Requires-Dist: pyodbc
